py2html/__init__.py
py2html/main.py
PY2HTML_Andre_Luis-0.0.1.dist-info/LICENSE
PY2HTML_Andre_Luis-0.0.1.dist-info/METADATA
PY2HTML_Andre_Luis-0.0.1.dist-info/WHEEL
PY2HTML_Andre_Luis-0.0.1.dist-info/top_level.txt
PY2HTML_Andre_Luis-0.0.1.dist-info/RECORD
