Metadata-Version: 2.1
Name: PY2HTML-Andre-Luis
Version: 0.0.1
Summary: Create html sites with python
Home-page: https://github.com/andreluispy/py2html
Author: André Luís
Author-email: andredev988@gmail.com
License: UNKNOWN
Platform: UNKNOWN
Classifier: Programming Language :: Python :: 3
Classifier: License :: OSI Approved :: MIT License
Classifier: Operating System :: OS Independent
Requires-Python: >=3.6
